[1,0,0,[["cc.JsonAsset",["_name","json"],1]],[[0,0,1,3]],[[0,"Step1",{"name":"Step1","name_zh":"比较","version":"1.0","description":{"en":"Returns 1 if the input value is greater than or equal to the Edge value, otherwise returns 0.","zh":"当输入值大于等于指定边缘值时返回 1，其余情况返回 0。"},"tags":["Core","Math","Round"],"input":[{"type":"float","name":"Edge","info":{"en":"Edge value","zh":"边缘值"}},{"type":"float","name":"Input","info":{"en":"Input value","zh":"输入值"}}],"output":[{"type":"float","name":"Output"}],"uniforms":{},"frags":{},"main":["float main(float Input, float Edge) {","    return step(Edge, Input);","}"]}]],0,0,[],[],[]]